scumpy/__init__.py
scumpy/scumpy.py
scumpy-2.55.dist-info/METADATA
scumpy-2.55.dist-info/WHEEL
scumpy-2.55.dist-info/top_level.txt
scumpy-2.55.dist-info/RECORD
